{
	"configurations" : 
	[
		{
			"directories" : 
			[
				{
					"build" : ".",
					"hasInstallRule" : true,
					"minimumCMakeVersion" : 
					{
						"string" : "3.20"
					},
					"projectIndex" : 0,
					"source" : ".",
					"targetIndexes" : 
					[
						0,
						1,
						2,
						3
					]
				}
			],
			"name" : "Debug",
			"projects" : 
			[
				{
					"directoryIndexes" : 
					[
						0
					],
					"name" : "calDAVClient",
					"targetIndexes" : 
					[
						0,
						1,
						2,
						3
					]
				}
			],
			"targets" : 
			[
				{
					"directoryIndex" : 0,
					"id" : "calDAVClient::@6890427a1f51a3e7e1df",
					"jsonFile" : "target-calDAVClient-Debug-535546db42a118fe468e.json",
					"name" : "calDAVClient",
					"projectIndex" : 0
				},
				{
					"directoryIndex" : 0,
					"id" : "calDAVClient_autogen::@6890427a1f51a3e7e1df",
					"jsonFile" : "target-calDAVClient_autogen-Debug-cd57b127f857afacbbfc.json",
					"name" : "calDAVClient_autogen",
					"projectIndex" : 0
				},
				{
					"directoryIndex" : 0,
					"id" : "calDAVClient_lib::@6890427a1f51a3e7e1df",
					"jsonFile" : "target-calDAVClient_lib-Debug-ab50a3d81449db6f9d42.json",
					"name" : "calDAVClient_lib",
					"projectIndex" : 0
				},
				{
					"directoryIndex" : 0,
					"id" : "calDAVClient_lib_autogen::@6890427a1f51a3e7e1df",
					"jsonFile" : "target-calDAVClient_lib_autogen-Debug-2d5fd7d74867bb845601.json",
					"name" : "calDAVClient_lib_autogen",
					"projectIndex" : 0
				}
			]
		}
	],
	"kind" : "codemodel",
	"paths" : 
	{
		"build" : "/Users/leonardoperugini/Desktop/Calendar-and-To-Do-list-CalDav/calDAVClient/cmake-build-debug",
		"source" : "/Users/leonardoperugini/Desktop/Calendar-and-To-Do-list-CalDav/calDAVClient"
	},
	"version" : 
	{
		"major" : 2,
		"minor" : 2
	}
}
